pseuserver/__init__.py
pseuserver/__main__.py
pseuserver/methods.py
pseuserver/resource.py
pseuserver/settings.py
pseuserver-3.1.1.dist-info/DESCRIPTION.rst
pseuserver-3.1.1.dist-info/METADATA
pseuserver-3.1.1.dist-info/RECORD
pseuserver-3.1.1.dist-info/WHEEL
pseuserver-3.1.1.dist-info/metadata.json
pseuserver-3.1.1.dist-info/top_level.txt
pseuserver-3.1.1.dist-info/zip-safe
tests/__init__.py
tests/test_api.py
tests/test_api_prefix.py
tests/test_methods.py
tests/test_pseuserver.py
tests/test_resource.py
utils/__init__.py
utils/cors.py
utils/crypto.py
