Metadata-Version: 2.0
Name: pseuserver
Version: 3.1.1
Summary: is a zero-coding restful API server inspired by Json-Server and Eve. It is designed to be used as fake restful api for development,  especially for people want to stick with Python stack. Setup process  is less than 1 minute. 
Home-page: https://github.com/harryho/pseu-server
Author: Harry Ho
Author-email: harry.ho_long@yahoo.com
License: MIT
Requires-Dist: Flask (>=0.8)
Requires-Dist: pseudb (>=3.2.0)
